cpi_tools/__init__.py
cpi_tools/aws_tools.py
cpi_tools/cpi_validation.py
cpi_tools/fuzzy_matching_cpi.py
cpi_tools/sharepoint_tools.py
cpi_tools/tracking_processing_tools.py
cpi_tools/tracking_processing_tools_v2.py
cpi_tools/tracking_processing_tools_v3.py
cpi_tools-0.4.1.dist-info/licenses/LICENSE
cpi_tools-0.4.1.dist-info/METADATA
cpi_tools-0.4.1.dist-info/WHEEL
cpi_tools-0.4.1.dist-info/top_level.txt
cpi_tools-0.4.1.dist-info/RECORD
