Metadata-Version: 2.4
Name: cpi_tools
Version: 0.4.1
Summary: Repository of functions used across CPI
Home-page: https://github.com/climatepolicydata/cpi_tools
Author: Jake Connolly, Nikita Marini, Eddie Dilworth
Author-email: datascience@cpiglobal.org
Classifier: Programming Language :: Python :: 3
Classifier: License :: OSI Approved :: MIT License
Classifier: Operating System :: OS Independent
Requires-Python: >=3.7
License-File: LICENSE
Dynamic: license-file
